{
  "version": "crDroid 9.10 v2023.10.20",
  "date": "1697804231",
  "variants": [
    {
      "name": "treble_arm64_bvN",
      "size": "946311276",
      "url": "https://github.com/naz664/crDroid_gsi/releases/tag/v2023.10.20/crDroid-9.10-arm64_bvN-Unofficial.img.xz"
    },
    {
      "name": "treble_arm64_bgN",
      "size": "1356718496",
      "url": "https://github.com/naz664/crDroid_gsi/releases/tag/v2023.10.20/crDroid-9.10-arm64_bgN-Unofficial.img.xz"
    },
    {
      "name": "treble_arm64_bgN-slim",
      "size": "1144021108",
      "url": "https://github.com/naz664/crDroid_gsi/releases/tag/v2023.10.20/crDroid-9.10-arm64_bgN-slim-Unofficial.img.xz"
    }
  ]
}
